bip39toolkit.py
bip39toolkit-0.1.1.data/scripts/bip39toolkit.py
bip39toolkit-0.1.1.dist-info/licenses/LICENSE
bip39toolkit-0.1.1.dist-info/METADATA
bip39toolkit-0.1.1.dist-info/WHEEL
bip39toolkit-0.1.1.dist-info/top_level.txt
bip39toolkit-0.1.1.dist-info/RECORD
