Metadata-Version: 2.4
Name: bip39toolkit
Version: 0.1.1
Summary: The BIP39 toolkit is a self-contained command line application, which provides an interface to generate, secret share and recover BIP39 mnemonic phrases.
Home-page: https://github.com/de-centralized-systems/bip39toolkit/
Author: Philipp Schindler and Aljosha Judmayer
Project-URL: Source, https://github.com/de-centralized-systems/bip39toolkit/
Project-URL: Bug Tracker, https://github.com/de-centralized-systems/bip39toolkit/issues
Classifier: Development Status :: 4 - Beta
Classifier: Environment :: Console
Classifier: License :: OSI Approved :: MIT License
Classifier: Programming Language :: Python :: 3.9
Classifier: Topic :: Security
Classifier: Topic :: Utilities
Requires-Python: >=3.9.0
License-File: LICENSE
Provides-Extra: dev
Requires-Dist: pytest; extra == "dev"
Requires-Dist: pytest-cov; extra == "dev"
Dynamic: author
Dynamic: classifier
Dynamic: description
Dynamic: description-content-type
Dynamic: home-page
Dynamic: license-file
Dynamic: project-url
Dynamic: provides-extra
Dynamic: requires-python
Dynamic: summary
